hxtz/__init__.py
hxtz/hxtz.py
hxtz-1.0.63.dist-info/LICENSE.txt
hxtz-1.0.63.dist-info/METADATA
hxtz-1.0.63.dist-info/WHEEL
hxtz-1.0.63.dist-info/top_level.txt
hxtz-1.0.63.dist-info/RECORD
