Metadata-Version: 2.1
Name: hxtz
Version: 1.0.63
Summary: me
Home-page: https://cn.bing.com/
Author: hxtz
Author-email: 1375151810@qq.com
License: UNKNOWN
Platform: UNKNOWN
Classifier: Programming Language :: Python :: 3
Classifier: License :: OSI Approved :: MIT License
Classifier: Operating System :: OS Independent
Requires-Python: >=3.7
Requires-Dist: requests
Requires-Dist: pandas
Requires-Dist: pywinauto
